abm/__init__.py
abm/_exports.py
abm/_helper/__init__.py
abm/_helper/argument_parser.py
abm/_helper/covariance_matrix.py
abm/_helper/create_map.py
abm/_helper/display.py
abm/_helper/get_dose_schedules.py
abm/_helper/get_model.py
abm/_helper/get_table.py
abm/_helper/helper.py
abm/_helper/initialize_parameter_table.py
abm/_helper/nested_map.py
abm/_helper/parameter.py
abm/_helper/parse_output_times.py
abm/_helper/parse_schedule.py
abm/_helper/parser.py
abm/_helper/posterior_sample_list_diagnostics.py
abm/_helper/profile_likelihood.py
abm/_helper/validate_columns.py
abm/_labelset.py
abm/_optimize.py
abm/_scan.py
abm/_scan_ast.py
abm/_sdk/__init__.py
abm/_sdk/array.py
abm/_sdk/assess.py
abm/_sdk/assess_metadata.py
abm/_sdk/client_interface.py
abm/_sdk/contract.py
abm/_sdk/data_frame.py
abm/_sdk/data_pipe.py
abm/_sdk/data_pipe_builder.py
abm/_sdk/data_pipe_result.py
abm/_sdk/data_type.py
abm/_sdk/data_type_parser.py
abm/_sdk/dataclass_helpers.py
abm/_sdk/distribution_sample.py
abm/_sdk/exceptions.py
abm/_sdk/expression.py
abm/_sdk/job.py
abm/_sdk/legacy.py
abm/_sdk/legacy_assess_metadata.py
abm/_sdk/likelihood/__init__.py
abm/_sdk/likelihood/allen.py
abm/_sdk/likelihood/base.py
abm/_sdk/likelihood/distributions/__init__.py
abm/_sdk/likelihood/distributions/base.py
abm/_sdk/likelihood/distributions/distributions.py
abm/_sdk/likelihood/distributions/histogram.py
abm/_sdk/likelihood/distributions/loguniform.py
abm/_sdk/likelihood/distributions/multivariate_lognormal.py
abm/_sdk/likelihood/distributions/multivariate_normal.py
abm/_sdk/likelihood/distributions/uniform.py
abm/_sdk/likelihood/measurements.py
abm/_sdk/ode_fisher_information_matrix.py
abm/_sdk/ode_gradient.py
abm/_sdk/ode_measurement_likelihood_sample.py
abm/_sdk/ode_model.py
abm/_sdk/ode_model_reference.py
abm/_sdk/ode_optimization.py
abm/_sdk/ode_optimization_batch.py
abm/_sdk/ode_optimization_configuration.py
abm/_sdk/ode_optimization_result.py
abm/_sdk/ode_parameter_posterior_sample.py
abm-2.2.2.dist-info/LICENSE
abm-2.2.2.dist-info/METADATA
abm-2.2.2.dist-info/WHEEL
abm-2.2.2.dist-info/RECORD
