Metadata-Version: 2.1
Name: abm
Version: 2.2.2
Summary: A Python client for the Applied BioMath platform
Home-page: https://github.com/certara/certara-iq-python-client
License: Proprietary
Author: ABM Support
Author-email: abm-support@certara.com
Requires-Python: >=3.12,<3.13
Classifier: Development Status :: 5 - Production/Stable
Classifier: Intended Audience :: Science/Research
Classifier: License :: Other/Proprietary License
Classifier: Operating System :: POSIX
Classifier: Programming Language :: Python :: 3
Classifier: Programming Language :: Python :: 3.12
Classifier: Topic :: Scientific/Engineering :: Medical Science Apps.
Requires-Dist: httpx (>=0.27,<0.28)
Requires-Dist: ipython (>=9.6,<10.0)
Requires-Dist: numpy (>=2.3,<3.0)
Requires-Dist: ordered-set (>=4.1,<5.0)
Requires-Dist: pandas (>=2.3,<3.0)
Requires-Dist: parsita (>=2.2,<2.3)
Requires-Dist: pint (>=0.25,<0.26)
Requires-Dist: prettytable (>=3.16,<4.0)
Requires-Dist: scipy (>=1.16,<2.0)
Requires-Dist: serialite (>=0.3,<0.4)
Requires-Dist: tabeline[pandas,polars] (>=0.6,<0.7)
Project-URL: Repository, https://github.com/certara/certara-iq-python-client
